firepit/__init__.py
firepit/cli.py
firepit/deref.py
firepit/exceptions.py
firepit/export.py
firepit/generator.py
firepit/paramstix.lark
firepit/pgcommon.py
firepit/pgstorage.py
firepit/props.py
firepit/query.py
firepit/raft.py
firepit/schemas.py
firepit/splint.py
firepit/splitter.py
firepit/sqlitestorage.py
firepit/sqlstorage.py
firepit/stix20.py
firepit/stix21.py
firepit/timestamp.py
firepit/validate.py
firepit/woodchipper.py
firepit/aio/__init__.py
firepit/aio/asyncpgstorage.py
firepit/aio/asyncstorage.py
firepit/aio/asyncwrapper.py
firepit/aio/ingest.py
firepit-2.3.35.dist-info/AUTHORS.rst
firepit-2.3.35.dist-info/LICENSE
firepit-2.3.35.dist-info/METADATA
firepit-2.3.35.dist-info/WHEEL
firepit-2.3.35.dist-info/entry_points.txt
firepit-2.3.35.dist-info/top_level.txt
firepit-2.3.35.dist-info/RECORD
