Metadata-Version: 2.1
Name: firepit
Version: 2.3.35
Summary: Columnar storage for STIX 2.0 observations.
Home-page: https://github.com/opencybersecurityalliance/firepit
Author: IBM Security
Author-email: pcoccoli@us.ibm.com
License: Apache Software License 2.0
Keywords: stix stix-shifter sql python
Platform: UNKNOWN
Classifier: Development Status :: 4 - Beta
Classifier: Topic :: Security
Classifier: Intended Audience :: Developers
Classifier: License :: OSI Approved :: Apache Software License
Classifier: Natural Language :: English
Classifier: Programming Language :: Python :: 3
Classifier: Programming Language :: Python :: 3.8
Classifier: Programming Language :: Python :: 3.9
Classifier: Programming Language :: Python :: 3.10
Classifier: Programming Language :: Python :: 3.11
Requires-Python: >=3.8
Provides-Extra: postgres
Provides-Extra: async-postgres
